setup.py
Flask_Encryptor.egg-info/PKG-INFO
Flask_Encryptor.egg-info/SOURCES.txt
Flask_Encryptor.egg-info/dependency_links.txt
Flask_Encryptor.egg-info/not-zip-safe
Flask_Encryptor.egg-info/requires.txt
Flask_Encryptor.egg-info/top_level.txt
flask_encryptor/__init__.py
flask_encryptor/models.py
flask_encryptor.egg-info/PKG-INFO
flask_encryptor.egg-info/SOURCES.txt
flask_encryptor.egg-info/dependency_links.txt
flask_encryptor.egg-info/not-zip-safe
flask_encryptor.egg-info/requires.txt
flask_encryptor.egg-info/top_level.txt