Metadata-Version: 1.1
Name: flask-encryptor
Version: 0.2.5
Summary: Flask extension helping encrypting users personal files
Home-page: https://github.com/Querdos/Flask-Encryptor
Author: Hamza ESSAYEGH
Author-email: hamza.essayegh@protonmail.com
License: BSD
Platform: any
Classifier: Environment :: Web Environment
Classifier: Intended Audience :: Developers
Classifier: License :: OSI Approved :: BSD License
Classifier: Operating System :: OS Independent
Classifier: Programming Language :: Python
Classifier: Topic :: Internet :: WWW/HTTP :: Dynamic Content
Classifier: Topic :: Software Development :: Libraries :: Python Modules
